[
  {
    "name": "Admin",
    "type": "NORMAL",
    "cores": [
      518379920
    ],
    "crypts": 34,
    "shape": "1x1"
  },
  {
    "name": "Altar",
    "type": "NORMAL",
    "cores": [
      1591923028,
      1958840063,
      -1927723170
    ],
    "crypts": 3,
    "secrets": 6,
    "shape": "L"
  },
  {
    "name": "Andesite",
    "type": "NORMAL",
    "cores": [
      -1701988142
    ],
    "secrets": 2,
    "shape": "1x1"
  },
  {
    "name": "Archway",
    "type": "NORMAL",
    "cores": [
      259768244,
      1440685825
    ],
    "crypts": 4,
    "secrets": 3,
    "shape": "1x2"
  },
  {
    "name": "Arrow Trap",
    "type": "NORMAL",
    "cores": [
      313879976
    ],
    "crypts": 1,
    "secrets": 1,
    "shape": "1x1"
  },
  {
    "name": "Atlas",
    "type": "NORMAL",
    "cores": [
      -190201621,
      1910997131,
      740650704,
      -2080722918
    ],
    "crypts": 5,
    "secrets": 6,
    "shape": "2x2"
  },
  {
    "name": "Balcony",
    "type": "NORMAL",
    "cores": [
      1765345183,
      2133731337
    ],
    "secrets": 4,
    "shape": "1x2"
  },
  {
    "name": "Banners",
    "type": "NORMAL",
    "cores": [
      -1092023380
    ],
    "crypts": 1,
    "secrets": 1,
    "shape": "1x1"
  },
  {
    "name": "Basement",
    "type": "NORMAL",
    "cores": [
      1491050733
    ],
    "secrets": 1,
    "shape": "1x1"
  },
  {
    "name": "Beams",
    "type": "NORMAL",
    "cores": [
      -1764045332
    ],
    "crypts": 2,
    "secrets": 2,
    "shape": "1x1"
  },
  {
    "name": "Big Red Flag",
    "type": "NORMAL",
    "cores": [
      -807913351
    ],
    "crypts": 1,
    "secrets": 2,
    "shape": "1x1"
  },
  {
    "name": "Black Flag",
    "type": "NORMAL",
    "cores": [
      -1779299819
    ],
    "crypts": 1,
    "secrets": 3,
    "shape": "1x1"
  },
  {
    "name": "Blood",
    "type": "BLOOD",
    "cores": [
      1898104308,
      698844034
    ],
    "shape": "1x1"
  },
  {
    "name": "Blue Skulls",
    "type": "NORMAL",
    "cores": [
      -1410316771
    ],
    "crypts": 4,
    "secrets": 1,
    "shape": "1x1"
  },
  {
    "name": "Boulder",
    "type": "PUZZLE",
    "cores": [
      -1129249963,
      1047612794,
      1280589896,
      -609854937
    ],
    "shape": "1x1"
  },
  {
    "name": "Bridges",
    "type": "NORMAL",
    "cores": [
      1024359556,
      454887921
    ],
    "crypts": 6,
    "secrets": 6,
    "shape": "1x2"
  },
  {
    "name": "Buttons",
    "type": "NORMAL",
    "cores": [
      -493713078,
      -1578136054,
      1033549564,
      112871973
    ],
    "crypts": 21,
    "secrets": 5,
    "trappedChests": 1,
    "shape": "2x2"
  },
  {
    "name": "Cage",
    "type": "NORMAL",
    "cores": [
      -407233803
    ],
    "secrets": 1,
    "shape": "1x1"
  },
  {
    "name": "Cages",
    "type": "NORMAL",
    "cores": [
      -1164795630
    ],
    "secrets": 2,
    "shape": "1x1"
  },
  {
    "name": "Carpets",
    "type": "NORMAL",
    "cores": [
      238642395,
      -76292695
    ],
    "crypts": 3,
    "secrets": 1,
    "shape": "1x1"
  },
  {
    "name": "Cathedral",
    "type": "NORMAL",
    "cores": [
      -1530782553,
      -1999467696,
      950592972,
      -508170344
    ],
    "crypts": 5,
    "secrets": 8,
    "shape": "2x2"
  },
  {
    "name": "Catwalk",
    "type": "NORMAL",
    "cores": [
      -1556782371,
      -2024953154,
      1179970013
    ],
    "crypts": 5,
    "secrets": 6,
    "shape": "1x3"
  },
  {
    "name": "Cell",
    "type": "NORMAL",
    "cores": [
      1560740373
    ],
    "secrets": 1,
    "shape": "1x1"
  },
  {
    "name": "Chains",
    "type": "NORMAL",
    "cores": [
      -448181487
    ],
    "secrets": 2,
    "shape": "1x1"
  },
  {
    "name": "Chambers",
    "type": "NORMAL",
    "cores": [
      -27291325,
      -2119802509,
      -546080393
    ],
    "crypts": 6,
    "secrets": 5,
    "shape": "L"
  },
  {
    "name": "Cobble Wall Pillar",
    "type": "NORMAL",
    "cores": [
      -170648742
    ],
    "crypts": 1,
    "secrets": 2,
    "shape": "1x1"
  },
  {
    "name": "Creeper Beams",
    "type": "PUZZLE",
    "cores": [
      1264110624,
      866773091,
      -1655263707
    ],
    "shape": "1x1"
  },
  {
    "name": "Criss-Cross",
    "type": "NORMAL",
    "cores": [
      -1879625096
    ],
    "crypts": 6,
    "secrets": 1,
    "shape": "1x1"
  },
  {
    "name": "Crypt",
    "type": "NORMAL",
    "cores": [
      1113194131,
      1376295224
    ],
    "crypts": 2,
    "secrets": 5,
    "shape": "1x2"
  },
  {
    "name": "Deathmite",
    "type": "NORMAL",
    "cores": [
      706341009,
      2089865315,
      -414187054
    ],
    "crypts": 4,
    "secrets": 6,
    "shape": "1x3"
  },
  {
    "name": "Default",
    "type": "CHAMPION",
    "cores": [
      -1637527174,
      -1199831932
    ],
    "shape": "1x1"
  },
  {
    "name": "Diagonal",
    "type": "NORMAL",
    "cores": [
      516895741,
      476976104,
      -959823640
    ],
    "crypts": 3,
    "secrets": 4,
    "shape": "1x3"
  },
  {
    "name": "Dino Site",
    "type": "NORMAL",
    "cores": [
      -678116754,
      -970680134,
      1735273877
    ],
    "crypts": 4,
    "secrets": 4,
    "shape": "L"
  },
  {
    "name": "Dip",
    "type": "NORMAL",
    "cores": [
      -1373895553
    ],
    "crypts": 3,
    "secrets": 2,
    "shape": "1x1"
  },
  {
    "name": "Dome",
    "type": "NORMAL",
    "cores": [
      -1468156116,
      291108944
    ],
    "crypts": 2,
    "secrets": 2,
    "shape": "1x1"
  },
  {
    "name": "Doors",
    "type": "NORMAL",
    "cores": [
      -811830702,
      551939185
    ],
    "crypts": 7,
    "secrets": 5,
    "shape": "1x2"
  },
  {
    "name": "Double Diamond",
    "type": "NORMAL",
    "cores": [
      1857926981
    ],
    "secrets": 3,
    "shape": "1x1"
  },
  {
    "name": "Dragon",
    "type": "CHAMPION",
    "cores": [
      -1334473473
    ],
    "shape": "1x1"
  },
  {
    "name": "Drop",
    "type": "NORMAL",
    "cores": [
      -1779237820
    ],
    "crypts": 6,
    "secrets": 2,
    "shape": "1x1"
  },
  {
    "name": "Dueces",
    "type": "NORMAL",
    "cores": [
      -697416341
    ],
    "crypts": 6,
    "secrets": 3,
    "trappedChests": 1,
    "shape": "1x1"
  },
  {
    "name": "Duncan",
    "type": "NORMAL",
    "cores": [
      -1999038851
    ],
    "secrets": 1,
    "shape": "1x1"
  },
  {
    "name": "End",
    "type": "NORMAL",
    "cores": [
      -531914593
    ],
    "crypts": 1,
    "secrets": 2,
    "shape": "1x1"
  },
  {
    "name": "Entrance",
    "type": "ENTRANCE",
    "cores": [
      -16485885,
      -47045487,
      77375583
    ],
    "shape": "1x1"
  },
  {
    "name": "Fairy",
    "type": "FAIRY",
    "cores": [
      -645035252
    ],
    "shape": "1x1"
  },
  {
    "name": "Flags",
    "type": "NORMAL",
    "cores": [
      -55302423,
      -611463932,
      -2069105515,
      908422074
    ],
    "crypts": 8,
    "secrets": 7,
    "shape": "2x2"
  },
  {
    "name": "Gold",
    "type": "NORMAL",
    "cores": [
      992885012,
      35550104
    ],
    "secrets": 1,
    "shape": "1x2"
  },
  {
    "name": "Golden Oasis",
    "type": "NORMAL",
    "cores": [
      178277726
    ],
    "crypts": 1,
    "secrets": 1,
    "shape": "1x1"
  },
  {
    "name": "Grand Library",
    "type": "NORMAL",
    "cores": [
      -1142842273,
      648931278
    ],
    "crypts": 2,
    "secrets": 4,
    "shape": "1x2"
  },
  {
    "name": "Granite",
    "type": "NORMAL",
    "cores": [
      -41110951
    ],
    "secrets": 2,
    "shape": "1x1"
  },
  {
    "name": "Grass Ruin",
    "type": "NORMAL",
    "cores": [
      -1049958927,
      438605094,
      2015882449,
      -1847986179
    ],
    "crypts": 4,
    "secrets": 3,
    "shape": "1x2"
  },
  {
    "name": "Gravel",
    "type": "NORMAL",
    "cores": [
      -1149900195,
      -558347945,
      1422441247,
      244770880
    ],
    "crypts": 2,
    "secrets": 6,
    "shape": "1x3"
  },
  {
    "name": "Hall",
    "type": "NORMAL",
    "cores": [
      -442394410
    ],
    "shape": "1x1"
  },
  {
    "name": "Hallway",
    "type": "NORMAL",
    "cores": [
      -1326659171,
      1051405699,
      -1454277723,
      1020848351
    ],
    "crypts": 1,
    "secrets": 3,
    "shape": "1x4"
  },
  {
    "name": "Higher Blaze",
    "type": "PUZZLE",
    "cores": [
      -1752027278,
      -1477567187
    ],
    "secrets": 1,
    "shape": "1x1"
  },
  {
    "name": "Ice Fill",
    "type": "PUZZLE",
    "cores": [
      -1871216735,
      72131612,
      -1404774853
    ],
    "shape": "1x1"
  },
  {
    "name": "Ice Path",
    "type": "PUZZLE",
    "cores": [
      -145184586
    ],
    "shape": "1x1"
  },
  {
    "name": "Jumping Skulls",
    "type": "NORMAL",
    "cores": [
      205151025
    ],
    "secrets": 1,
    "shape": "1x1"
  },
  {
    "name": "King Midas",
    "type": "CHAMPION",
    "cores": [
      -1916395486
    ],
    "crypts": 1,
    "shape": "1x1"
  },
  {
    "name": "Knight",
    "type": "NORMAL",
    "cores": [
      -1519890056
    ],
    "secrets": 3,
    "shape": "1x1"
  },
  {
    "name": "Lava Pit",
    "type": "RARE",
    "cores": [
      -695235565
    ],
    "secrets": 3,
    "shape": "1x1"
  },
  {
    "name": "Lava Ravine",
    "type": "NORMAL",
    "cores": [
      1131013667,
      2036450719,
      -854539536
    ],
    "crypts": 4,
    "secrets": 6,
    "shape": "L"
  },
  {
    "name": "Layers",
    "type": "NORMAL",
    "cores": [
      965792061,
      -923498250,
      161195688
    ],
    "secrets": 8,
    "shape": "L"
  },
  {
    "name": "Leaves",
    "type": "NORMAL",
    "cores": [
      643669164
    ],
    "crypts": 1,
    "secrets": 1,
    "shape": "1x1"
  },
  {
    "name": "Locked Away",
    "type": "NORMAL",
    "cores": [
      706748439
    ],
    "crypts": 1,
    "secrets": 1,
    "shape": "1x1"
  },
  {
    "name": "Logs",
    "type": "NORMAL",
    "cores": [
      1783642819
    ],
    "secrets": 4,
    "shape": "1x1"
  },
  {
    "name": "Long Hall",
    "type": "NORMAL",
    "cores": [
      587195362
    ],
    "crypts": 3,
    "secrets": 3,
    "shape": "1x1"
  },
  {
    "name": "Lots Of Floors",
    "type": "NORMAL",
    "cores": [
      -1112550874
    ],
    "crypts": 1,
    "secrets": 3,
    "shape": "1x1"
  },
  {
    "name": "Lower Blaze",
    "type": "PUZZLE",
    "cores": [
      -441650545,
      911747293
    ],
    "secrets": 1,
    "shape": "1x1"
  },
  {
    "name": "Mage",
    "type": "NORMAL",
    "cores": [
      1475692888,
      925853313
    ],
    "secrets": 4,
    "shape": "1x2"
  },
  {
    "name": "Market",
    "type": "NORMAL",
    "cores": [
      945592478,
      -1882970229,
      300771790
    ],
    "crypts": 4,
    "secrets": 5,
    "shape": "L"
  },
  {
    "name": "Melon",
    "type": "NORMAL",
    "cores": [
      -1164821574,
      578838281,
      -1740446783
    ],
    "crypts": 4,
    "secrets": 7,
    "shape": "L"
  },
  {
    "name": "Mines",
    "type": "NORMAL",
    "cores": [
      -42175953,
      1905421134,
      -1565557409,
      -892257050
    ],
    "crypts": 11,
    "secrets": 10,
    "shape": "2x2"
  },
  {
    "name": "Trinity",
    "type": "RARE",
    "cores": [
      302128578
    ],
    "crypts": 3,
    "secrets": 4,
    "shape": "1x1"
  },
  {
    "name": "Mirror",
    "type": "NORMAL",
    "cores": [
      76347246
    ],
    "secrets": 1,
    "shape": "1x1"
  },
  {
    "name": "Mossy",
    "type": "NORMAL",
    "cores": [
      -751626537,
      705890228,
      1402530236,
      -408036566
    ],
    "crypts": 2,
    "secrets": 4,
    "shape": "1x4"
  },
  {
    "name": "Multicolored",
    "type": "NORMAL",
    "cores": [
      -543960045
    ],
    "secrets": 1,
    "shape": "1x1"
  },
  {
    "name": "Mural",
    "type": "NORMAL",
    "cores": [
      -743021993
    ],
    "secrets": 1,
    "shape": "1x1"
  },
  {
    "name": "Museum",
    "type": "NORMAL",
    "cores": [
      -1505871564,
      1250712883,
      898168212,
      -95130049
    ],
    "crypts": 4,
    "secrets": 5,
    "shape": "2x2"
  },
  {
    "name": "Mushroom",
    "type": "NORMAL",
    "cores": [
      1461632797
    ],
    "secrets": 1,
    "shape": "1x1"
  },
  {
    "name": "New Trap",
    "type": "TRAP",
    "cores": [
      -1471076910,
      1043953833,
      -686376510,
      1851993785
    ],
    "crypts": 1,
    "secrets": 3,
    "trappedChests": 1,
    "shape": "1x1"
  },
  {
    "name": "Old Trap",
    "type": "TRAP",
    "cores": [
      1590699551,
      -85564220
    ],
    "crypts": 2,
    "secrets": 4,
    "shape": "1x1"
  },
  {
    "name": "Overgrown",
    "type": "NORMAL",
    "cores": [
      -726297434
    ],
    "secrets": 3,
    "shape": "1x1"
  },
  {
    "name": "Overgrown Chains",
    "type": "NORMAL",
    "cores": [
      95969553
    ],
    "crypts": 1,
    "secrets": 2,
    "shape": "1x1"
  },
  {
    "name": "Painting",
    "type": "NORMAL",
    "cores": [
      -725718835
    ],
    "secrets": 2,
    "shape": "1x1"
  },
  {
    "name": "Pedestal",
    "type": "NORMAL",
    "cores": [
      -1792508076,
      1549240174
    ],
    "crypts": 1,
    "secrets": 5,
    "shape": "1x2"
  },
  {
    "name": "Perch",
    "type": "NORMAL",
    "cores": [
      -444976906
    ],
    "crypts": 1,
    "secrets": 2,
    "shape": "1x1"
  },
  {
    "name": "Pipes",
    "type": "NORMAL",
    "cores": [
      464805832,
      1942538809,
      -1208278490,
      1917735700
    ],
    "crypts": 9,
    "secrets": 7,
    "shape": "1x4"
  },
  {
    "name": "Pirate",
    "type": "NORMAL",
    "cores": [
      884966227,
      252263088,
      2061161472
    ],
    "crypts": 2,
    "secrets": 6,
    "shape": "L"
  },
  {
    "name": "Pit",
    "type": "NORMAL",
    "cores": [
      -1477466539,
      -19869269,
      419868305,
      968300381,
      634229450
    ],
    "crypts": 4,
    "secrets": 5,
    "shape": "1x4"
  },
  {
    "name": "Pressure Plates",
    "type": "NORMAL",
    "cores": [
      763731417,
      -2105744124,
      2023286596
    ],
    "crypts": 6,
    "secrets": 6,
    "shape": "1x2"
  },
  {
    "name": "Prison Cell",
    "type": "NORMAL",
    "cores": [
      845343581
    ],
    "crypts": 1,
    "secrets": 1,
    "shape": "1x1"
  },
  {
    "name": "Purple Flags",
    "type": "NORMAL",
    "cores": [
      1500789482,
      664490773
    ],
    "crypts": 7,
    "secrets": 5,
    "shape": "1x2"
  },
  {
    "name": "Quad Lava",
    "type": "NORMAL",
    "cores": [
      1865354448
    ],
    "secrets": 2,
    "shape": "1x1"
  },
  {
    "name": "Quartz Knight",
    "type": "NORMAL",
    "cores": [
      667192030,
      -22728251,
      -1420471034,
      -215394360
    ],
    "crypts": 9,
    "secrets": 7,
    "shape": "1x4"
  },
  {
    "name": "Quiz",
    "type": "PUZZLE",
    "cores": [
      -1517679865,
      127714189
    ],
    "shape": "1x1"
  },
  {
    "name": "Raccoon",
    "type": "NORMAL",
    "cores": [
      -1723880923
    ],
    "crypts": 2,
    "secrets": 4,
    "shape": "1x1"
  },
  {
    "name": "Rail Track",
    "type": "RARE",
    "cores": [
      -1362847550
    ],
    "crypts": 3,
    "secrets": 3,
    "shape": "1x1"
  },
  {
    "name": "Rails",
    "type": "NORMAL",
    "cores": [
      -746461328,
      497837740,
      -1272603595,
      -1882412922
    ],
    "crypts": 1,
    "secrets": 9,
    "shape": "2x2"
  },
  {
    "name": "Rare Carpets",
    "type": "RARE",
    "cores": [
      1613728006
    ],
    "secrets": 1,
    "shape": "1x1"
  },
  {
    "name": "Rare Overgrown",
    "type": "RARE",
    "cores": [
      -1907291752
    ],
    "secrets": 3,
    "shape": "1x1"
  },
  {
    "name": "Rare Pillars",
    "type": "RARE",
    "cores": [
      -609209015
    ],
    "secrets": 1,
    "shape": "1x1"
  },
  {
    "name": "Red Blue",
    "type": "NORMAL",
    "cores": [
      794366741,
      -443330283,
      -362002608,
      -608091458
    ],
    "crypts": 1,
    "secrets": 4,
    "shape": "1x3"
  },
  {
    "name": "Red Green",
    "type": "NORMAL",
    "cores": [
      -1800029469
    ],
    "crypts": 2,
    "secrets": 3,
    "shape": "1x1"
  },
  {
    "name": "Redstone Crypt",
    "type": "NORMAL",
    "cores": [
      1446016334,
      -889320918
    ],
    "secrets": 3,
    "shape": "1x1"
  },
  {
    "name": "Redstone Key",
    "type": "NORMAL",
    "cores": [
      684588480,
      -1986945620
    ],
    "crypts": 4,
    "secrets": 3,
    "trappedChests": 1,
    "shape": "1x1"
  },
  {
    "name": "Redstone Warrior",
    "type": "NORMAL",
    "cores": [
      217300640,
      -380862700
    ],
    "crypts": 4,
    "secrets": 3,
    "shape": "1x2"
  },
  {
    "name": "Ritual",
    "type": "NORMAL",
    "cores": [
      -610787478
    ],
    "crypts": 1,
    "secrets": 3,
    "shape": "1x1"
  },
  {
    "name": "Sand Dragon",
    "type": "RARE",
    "cores": [
      1781758146
    ],
    "crypts": 1,
    "secrets": 1,
    "shape": "1x1"
  },
  {
    "name": "Sarcophagus",
    "type": "NORMAL",
    "cores": [
      -1167774036,
      -771559429
    ],
    "crypts": 1,
    "secrets": 3,
    "shape": "1x1"
  },
  {
    "name": "Scaffolding",
    "type": "NORMAL",
    "cores": [
      -2146618657,
      -2091078305
    ],
    "secrets": 2,
    "shape": "1x1"
  },
  {
    "name": "Shadow Assassin",
    "type": "CHAMPION",
    "cores": [
      397211721
    ],
    "crypts": 2,
    "shape": "1x1"
  },
  {
    "name": "Silver Sword",
    "type": "NORMAL",
    "cores": [
      -1899702429
    ],
    "secrets": 1,
    "shape": "1x1"
  },
  {
    "name": "Skull",
    "type": "NORMAL",
    "cores": [
      -1554372511,
      80464378
    ],
    "secrets": 2,
    "shape": "1x2"
  },
  {
    "name": "Slabs",
    "type": "NORMAL",
    "cores": [
      568922940
    ],
    "crypts": 2,
    "secrets": 2,
    "shape": "1x1"
  },
  {
    "name": "Slime",
    "type": "NORMAL",
    "cores": [
      419670099,
      136252599,
      878407749
    ],
    "crypts": 1,
    "secrets": 5,
    "trappedChests": 1,
    "shape": "1x3"
  },
  {
    "name": "Sloth",
    "type": "NORMAL",
    "cores": [
      -566399217
    ],
    "crypts": 1,
    "secrets": 1,
    "shape": "1x1"
  },
  {
    "name": "Small Stairs",
    "type": "NORMAL",
    "cores": [
      -998001944
    ],
    "crypts": 1,
    "secrets": 2,
    "shape": "1x1"
  },
  {
    "name": "Small Waterfall",
    "type": "NORMAL",
    "cores": [
      -1188349447
    ],
    "crypts": 5,
    "secrets": 2,
    "shape": "1x1"
  },
  {
    "name": "Spider",
    "type": "NORMAL",
    "cores": [
      -716030238,
      -1647063650,
      -40178107
    ],
    "crypts": 3,
    "secrets": 9,
    "shape": "L"
  },
  {
    "name": "Spikes",
    "type": "NORMAL",
    "cores": [
      1484939648
    ],
    "crypts": 2,
    "secrets": 3,
    "shape": "1x1"
  },
  {
    "name": "Staircase",
    "type": "NORMAL",
    "cores": [
      -151940807
    ],
    "crypts": 2,
    "secrets": 3,
    "shape": "1x1"
  },
  {
    "name": "Stairs",
    "type": "NORMAL",
    "cores": [
      157642096,
      1758646790,
      -265444784,
      -2033694003
    ],
    "crypts": 1,
    "secrets": 4,
    "shape": "2x2"
  },
  {
    "name": "Steps",
    "type": "NORMAL",
    "cores": [
      755816704,
      -340486787
    ],
    "crypts": 1,
    "secrets": 1,
    "shape": "1x1"
  },
  {
    "name": "Stone Window",
    "type": "RARE",
    "cores": [
      -1740718028
    ],
    "crypts": 1,
    "secrets": 2,
    "shape": "1x1"
  },
  {
    "name": "Supertall",
    "type": "NORMAL",
    "cores": [
      -296996262,
      1395242314,
      -1760780706,
      -1867603567
    ],
    "crypts": 6,
    "secrets": 6,
    "shape": "2x2"
  },
  {
    "name": "Teleport Maze",
    "type": "PUZZLE",
    "cores": [
      799715466
    ],
    "shape": "1x1"
  },
  {
    "name": "Temple",
    "type": "NORMAL",
    "cores": [
      1575914755
    ],
    "secrets": 3,
    "shape": "1x1"
  },
  {
    "name": "Three Floors",
    "type": "RARE",
    "cores": [
      -1444508608
    ],
    "secrets": 1,
    "shape": "1x1"
  },
  {
    "name": "Three Weirdos",
    "type": "PUZZLE",
    "cores": [
      -2056613688
    ],
    "shape": "1x1"
  },
  {
    "name": "Tic Tac Toe",
    "type": "PUZZLE",
    "cores": [
      -738945309,
      29612250
    ],
    "secrets": 1,
    "shape": "1x1"
  },
  {
    "name": "Tombstone",
    "type": "RARE",
    "cores": [
      535698739
    ],
    "secrets": 2,
    "shape": "1x1"
  },
  {
    "name": "Tomioka",
    "type": "NORMAL",
    "cores": [
      -1191537425
    ],
    "shape": "1x1"
  },
  {
    "name": "Vinny 8 Ball",
    "type": "RARE",
    "cores": [
      872815555
    ],
    "secrets": 1,
    "shape": "1x1"
  },
  {
    "name": "Water",
    "type": "NORMAL",
    "cores": [
      -333637832
    ],
    "secrets": 2,
    "shape": "1x1"
  },
  {
    "name": "Water Board",
    "type": "PUZZLE",
    "cores": [
      379499781,
      -1229365170,
      -589525429
    ],
    "shape": "1x1"
  },
  {
    "name": "Waterfall",
    "type": "NORMAL",
    "cores": [
      90256084,
      228212335,
      -1682661340,
      520419865
    ],
    "crypts": 3,
    "secrets": 8,
    "shape": "1x4"
  },
  {
    "name": "Well",
    "type": "NORMAL",
    "cores": [
      629394370,
      1261773246,
      1276013917
    ],
    "crypts": 5,
    "secrets": 7,
    "shape": "L"
  },
  {
    "name": "Withermancer",
    "type": "NORMAL",
    "cores": [
      902780459,
      1963543962,
      1140917779
    ],
    "crypts": 6,
    "secrets": 4,
    "shape": "L"
  },
  {
    "name": "Wizard",
    "type": "NORMAL",
    "cores": [
      -1164862049,
      222124420,
      926568393
    ],
    "crypts": 8,
    "secrets": 4,
    "shape": "1x3"
  },
  {
    "name": "Zodd",
    "type": "NORMAL",
    "cores": [
      -1403940419
    ],
    "crypts": 1,
    "secrets": 1,
    "shape": "1x1"
  }
]